{
  "page_id": "eea2d81c-26d2-4925-bc52-9fc707cb7d99",
  "title": "Regularized ensemble learning for prediction and risk factors assessment of students at risk in the post-COVID era",
  "properties": {
    "Keywords/Type": {
      "id": "%2F7eo",
      "type": "multi_select",
      "multi_select": [
        {
          "id": "817f2854-4082-457f-920e-b5f83670f166",
          "name": "Ensemble Learning",
          "color": "default"
        },
        {
          "id": "bfd6aad4-710e-47cc-b766-a69bd2bac7b8",
          "name": "Students at risk",
          "color": "pink"
        },
        {
          "id": "d10c622d-7224-4643-bd2e-a1c8314875e4",
          "name": "Classification",
          "color": "yellow"
        },
        {
          "id": "f4d5901d-d430-45dd-9cd5-13ea8392171a",
          "name": "Face-to-Face Learning",
          "color": "red"
        },
        {
          "id": "507f0c40-812f-48b3-b58e-98e2da8134e3",
          "name": "Covid-19",
          "color": "red"
        }
      ]
    },
    "Search Strategy": {
      "id": "%3A%3E%7C%3A",
      "type": "rich_text",
      "rich_text": [
        {
          "type": "text",
          "text": {
            "content": "\"At-risk students\" AND \"Machine Learning”",
            "link": null
          },
          "annotations": {
            "bold": false,
            "italic": false,
            "strikethrough": false,
            "underline": false,
            "code": false,
            "color": "default"
          },
          "plain_text": "\"At-risk students\" AND \"Machine Learning”",
          "href": null
        }
      ]
    },
    "AI summary": {
      "id": "%40X%3D%3A",
      "type": "rich_text",
      "rich_text": []
    },
    "Learner Population": {
      "id": "%40hny",
      "type": "select",
      "select": {
        "id": "7940a14a-7ea0-41a0-820f-d08024337f8c",
        "name": "Higher Education (Not Course Related)",
        "color": "brown"
      }
    },
    "Year": {
      "id": "Blir",
      "type": "number",
      "number": 2024
    },
    "Article Type": {
      "id": "FG%3A%60",
      "type": "multi_select",
      "multi_select": [
        {
          "id": "h=IE",
          "name": "Q1 Journal",
          "color": "gray"
        }
      ]
    },
    "Learner Representation": {
      "id": "FdHu",
      "type": "multi_select",
      "multi_select": [
        {
          "id": "trX]",
          "name": "Static Aggregate",
          "color": "green"
        }
      ]
    },
    "Journal": {
      "id": "Popq",
      "type": "rich_text",
      "rich_text": [
        {
          "type": "text",
          "text": {
            "content": "Scientific Reports",
            "link": null
          },
          "annotations": {
            "bold": false,
            "italic": false,
            "strikethrough": false,
            "underline": false,
            "code": false,
            "color": "default"
          },
          "plain_text": "Scientific Reports",
          "href": null
        }
      ]
    },
    "Course-Agnostic Approach": {
      "id": "SW%7Bb",
      "type": "checkbox",
      "checkbox": true
    },
    "Status": {
      "id": "UMCM",
      "type": "status",
      "status": {
        "id": "bsf^",
        "name": "Accepted For Performance Prediction Task",
        "color": "green"
      }
    },
    "Results": {
      "id": "UMFh",
      "type": "checkbox",
      "checkbox": true
    },
    "Discussion": {
      "id": "W%5COz",
      "type": "checkbox",
      "checkbox": true
    },
    "Related Work": {
      "id": "%5Ec%5D_",
      "type": "checkbox",
      "checkbox": false
    },
    "Deployed/ Deployable": {
      "id": "%60bGZ",
      "type": "select",
      "select": {
        "id": "3dbf9971-3fdf-4eee-a449-3d26ee597e94",
        "name": "Prototype",
        "color": "red"
      }
    },
    "Abstract": {
      "id": "cswx",
      "type": "checkbox",
      "checkbox": true
    },
    "Introduction": {
      "id": "d%40Ow",
      "type": "checkbox",
      "checkbox": false
    },
    "Platform": {
      "id": "eGsN",
      "type": "rich_text",
      "rich_text": [
        {
          "type": "text",
          "text": {
            "content": "Google Scholar",
            "link": null
          },
          "annotations": {
            "bold": false,
            "italic": false,
            "strikethrough": false,
            "underline": false,
            "code": false,
            "color": "default"
          },
          "plain_text": "Google Scholar",
          "href": null
        }
      ]
    },
    "Limitations": {
      "id": "g%3F_D",
      "type": "checkbox",
      "checkbox": false
    },
    "Conclusion": {
      "id": "gXSx",
      "type": "checkbox",
      "checkbox": false
    },
    "Status_1": {
      "id": "h%3AFo",
      "type": "status",
      "status": {
        "id": "l;I]",
        "name": "N\\A",
        "color": "green"
      }
    },
    "Methods": {
      "id": "l%3Bbh",
      "type": "checkbox",
      "checkbox": true
    },
    "Work Nature": {
      "id": "oJe%5C",
      "type": "multi_select",
      "multi_select": [
        {
          "id": "|alu",
          "name": "Backtested with data from Previous Students",
          "color": "brown"
        }
      ]
    },
    "Motive For Exclusion": {
      "id": "pPy_",
      "type": "rich_text",
      "rich_text": []
    },
    "Completed": {
      "id": "qGBj",
      "type": "date",
      "date": {
        "start": "2024-08-06T00:00:00.000+01:00",
        "end": "2025-04-27T01:42:00.000+01:00",
        "time_zone": null
      }
    },
    "Author": {
      "id": "qNw_",
      "type": "rich_text",
      "rich_text": [
        {
          "type": "text",
          "text": {
            "content": "Khan et al.",
            "link": null
          },
          "annotations": {
            "bold": false,
            "italic": false,
            "strikethrough": false,
            "underline": false,
            "code": false,
            "color": "default"
          },
          "plain_text": "Khan et al.",
          "href": null
        }
      ]
    },
    "Date of Retrieval": {
      "id": "u%5DsD",
      "type": "date",
      "date": {
        "start": "2024-08-01",
        "end": null,
        "time_zone": null
      }
    },
    "Type": {
      "id": "%7Cs%7BS",
      "type": "multi_select",
      "multi_select": [
        {
          "id": "2705d9b4-cb5e-480a-ae96-365359960058",
          "name": "Student Performance",
          "color": "green"
        },
        {
          "id": "c928d68b-d25f-423a-b242-c67843bf6ed7",
          "name": "Deep Learning",
          "color": "red"
        }
      ]
    },
    "Name": {
      "id": "title",
      "type": "title",
      "title": [
        {
          "type": "text",
          "text": {
            "content": "Regularized ensemble learning for prediction and risk factors assessment of students at risk in the post-COVID era",
            "link": null
          },
          "annotations": {
            "bold": false,
            "italic": false,
            "strikethrough": false,
            "underline": false,
            "code": false,
            "color": "default"
          },
          "plain_text": "Regularized ensemble learning for prediction and risk factors assessment of students at risk in the post-COVID era",
          "href": null
        }
      ]
    }
  },
  "tables": [
    {
      "block_id": "1e24750c-f3ba-8085-aaae-ec2eb2bf83fa",
      "heading": "Summary Table PRED",
      "rows": [
        [
          "Task",
          "Context",
          "Teaching Method",
          "Student Performance Definition",
          "Target",
          "Students",
          "Courses",
          "Data sources",
          "Features",
          "Moment of Prediction",
          "Preprocessing Details",
          "Models",
          "Assessment Strategy",
          "Performance Metric: Best Model",
          "Comments",
          "Limitations"
        ],
        [
          "Classification",
          "Higher Education",
          "E-Learning",
          "Post-Covid in Program GPA",
          "GPA above 3 (1) vs Not (0)",
          "245 learners",
          "Courses at a Pakistani University",
          "Student Characteristics, Performance  Before Covid, Performance During Covid, Questionnaires",
          "[Faculty of the student, Gender, Age, Nationality, Status, Level of study, Academic performance during the COVID-19, Subjects in which student excels academically after COVID-19, Subjects in which student excels academically during COVID-19, Completing assignments, Reviewing material covered in lecture, In-class interaction, Transition from online to physical learning, Difficulty in readjusting to the traditional classroom after the COVID-19, Attendance after the COVID-19 restrictions, Post COVID-19 engagement in learning, Post COVID-19 period collaboration and peers interaction, Managing workload after the COVID-19, Efficiency in physical exams against online assessments, Difficulty concentrating or staying focused in class after the COVID-19, Time management after the COVID-19 restrictions, Effect of face-to-face interaction with teachers and classmates on learning, Effect of structure daily routine on study, Access to learning resources after restrictions, Indicator whether a prerequisite courses is taken during the COVID-19, Understanding the importance of pre-requisite, Level of difficulty in courses with pre-requisite done during the pandemic, GPA in the last semester during COVID-19 restriction, Internet connectivity, Class attendance after the COVID-19 restrictions, Effect of financial stress due the pandemic on learning, Lack of motivation due to COVID-19 related financial problems, Compromises or sacrifices due to financial constraints, Delays or disruptions in studies due to financial difficulty",
          "Before end of program ",
          "Authors extracted data from administrative data and used as input for multiple ML algorithms.\n\nTarget variable awas binarizxed from actual GPA value.\n\nAuthors look at different forms of pruning for a Random Forest:\n\nOOB sampling\nSub-sampling\nSub-Bagging.\n\nAuthors also explore the effective of training dataset size: 70%, 80% and 90%.",
          "ExNRule, kNN, WkNN, RF, SVM, NN, LDA, OTE-IND, OTE-OOB, OTE-SUB",
          "1000- Repeated Holdout Method",
          "{Accuracy: 0.872 - OTE-OOB with 90%, Cohen’s Kappa: 0.701 - OTE-OOB with 70%, Sensitivity: 0.767 - OTE-SUB with 80%, Brier Score: 0.110 - OTE-IND with 80%}",
          "This work is meant to explore how students who had part of their education during COVID and authors look to see how they perform after returning. ",
          "Small sample size. \n\nDoes not consider behavioral data."
        ]
      ],
      "index": 7
    }
  ],
  "blocks": [
    {
      "id": "7df4cfa5-9ff1-47c7-8dff-a5af6b8f69df",
      "type": "heading_2",
      "text": "Abstract",
      "raw": {
        "object": "block",
        "id": "7df4cfa5-9ff1-47c7-8dff-a5af6b8f69df",
        "parent": {
          "type": "page_id",
          "page_id": "eea2d81c-26d2-4925-bc52-9fc707cb7d99"
        },
        "created_time": "2024-08-06T14:29:00.000Z",
        "last_edited_time": "2024-08-06T14:29:00.000Z",
        "created_by": {
          "object": "user",
          "id": "20a7795c-3622-4527-bd13-5ddbf48dc31d"
        },
        "last_edited_by": {
          "object": "user",
          "id": "20a7795c-3622-4527-bd13-5ddbf48dc31d"
        },
        "has_children": false,
        "in_trash": false,
        "type": "heading_2",
        "heading_2": {
          "rich_text": [
            {
              "type": "text",
              "text": {
                "content": "Abstract",
                "link": null
              },
              "annotations": {
                "bold": false,
                "italic": false,
                "strikethrough": false,
                "underline": false,
                "code": false,
                "color": "default"
              },
              "plain_text": "Abstract",
              "href": null
            }
          ],
          "is_toggleable": false,
          "color": "default"
        },
        "archived": false
      }
    },
    {
      "id": "74670c11-02b2-4eab-938b-d4ffa033b537",
      "type": "paragraph",
      "text": "The transition back to face to fface learning may have hindered the ability of some students to learn. After all, COVID demanded a substantial change to one’s study habits and it may have been hard for some students to go back to the previous normal. Therefore, it is important to understand what potential risk factors exist for low performance. ",
      "raw": {
        "object": "block",
        "id": "74670c11-02b2-4eab-938b-d4ffa033b537",
        "parent": {
          "type": "page_id",
          "page_id": "eea2d81c-26d2-4925-bc52-9fc707cb7d99"
        },
        "created_time": "2024-08-06T14:29:00.000Z",
        "last_edited_time": "2024-08-06T14:31:00.000Z",
        "created_by": {
          "object": "user",
          "id": "20a7795c-3622-4527-bd13-5ddbf48dc31d"
        },
        "last_edited_by": {
          "object": "user",
          "id": "20a7795c-3622-4527-bd13-5ddbf48dc31d"
        },
        "has_children": false,
        "in_trash": false,
        "type": "paragraph",
        "paragraph": {
          "rich_text": [
            {
              "type": "text",
              "text": {
                "content": "The transition back to face to fface learning may have hindered the ability of some students to learn. After all, COVID demanded a substantial change to one’s study habits and it may have been hard for some students to go back to the previous normal. Therefore, it is important to understand what potential risk factors exist for low performance. ",
                "link": null
              },
              "annotations": {
                "bold": false,
                "italic": false,
                "strikethrough": false,
                "underline": false,
                "code": false,
                "color": "default"
              },
              "plain_text": "The transition back to face to fface learning may have hindered the ability of some students to learn. After all, COVID demanded a substantial change to one’s study habits and it may have been hard for some students to go back to the previous normal. Therefore, it is important to understand what potential risk factors exist for low performance. ",
              "href": null
            }
          ],
          "icon": null,
          "color": "default"
        },
        "archived": false
      }
    },
    {
      "id": "71c648e2-1013-4287-993d-cfb06e7a4878",
      "type": "paragraph",
      "text": "",
      "raw": {
        "object": "block",
        "id": "71c648e2-1013-4287-993d-cfb06e7a4878",
        "parent": {
          "type": "page_id",
          "page_id": "eea2d81c-26d2-4925-bc52-9fc707cb7d99"
        },
        "created_time": "2024-08-06T14:31:00.000Z",
        "last_edited_time": "2024-08-06T14:31:00.000Z",
        "created_by": {
          "object": "user",
          "id": "20a7795c-3622-4527-bd13-5ddbf48dc31d"
        },
        "last_edited_by": {
          "object": "user",
          "id": "20a7795c-3622-4527-bd13-5ddbf48dc31d"
        },
        "has_children": false,
        "in_trash": false,
        "type": "paragraph",
        "paragraph": {
          "rich_text": [],
          "icon": null,
          "color": "default"
        },
        "archived": false
      }
    },
    {
      "id": "98315ce3-885a-4a2a-8dce-7de13bd57e0f",
      "type": "paragraph",
      "text": "Standard ML models often find it hard to identify insights that may be useful for the design of early interventions. To address this, the authors create a Random Forest trained under 3 distinct pruning paradigms:",
      "raw": {
        "object": "block",
        "id": "98315ce3-885a-4a2a-8dce-7de13bd57e0f",
        "parent": {
          "type": "page_id",
          "page_id": "eea2d81c-26d2-4925-bc52-9fc707cb7d99"
        },
        "created_time": "2024-08-06T14:31:00.000Z",
        "last_edited_time": "2024-08-06T14:33:00.000Z",
        "created_by": {
          "object": "user",
          "id": "20a7795c-3622-4527-bd13-5ddbf48dc31d"
        },
        "last_edited_by": {
          "object": "user",
          "id": "20a7795c-3622-4527-bd13-5ddbf48dc31d"
        },
        "has_children": true,
        "in_trash": false,
        "type": "paragraph",
        "paragraph": {
          "rich_text": [
            {
              "type": "text",
              "text": {
                "content": "Standard ML models often find it hard to identify insights that may be useful for the design of early interventions. To address this, the authors create a Random Forest trained under 3 distinct pruning paradigms:",
                "link": null
              },
              "annotations": {
                "bold": false,
                "italic": false,
                "strikethrough": false,
                "underline": false,
                "code": false,
                "color": "default"
              },
              "plain_text": "Standard ML models often find it hard to identify insights that may be useful for the design of early interventions. To address this, the authors create a Random Forest trained under 3 distinct pruning paradigms:",
              "href": null
            }
          ],
          "icon": null,
          "color": "default"
        },
        "archived": false
      }
    },
    {
      "id": "7c3b1594-faae-4801-8ade-fd578f89990a",
      "type": "paragraph",
      "text": "",
      "raw": {
        "object": "block",
        "id": "7c3b1594-faae-4801-8ade-fd578f89990a",
        "parent": {
          "type": "page_id",
          "page_id": "eea2d81c-26d2-4925-bc52-9fc707cb7d99"
        },
        "created_time": "2024-08-06T14:33:00.000Z",
        "last_edited_time": "2024-08-06T14:33:00.000Z",
        "created_by": {
          "object": "user",
          "id": "20a7795c-3622-4527-bd13-5ddbf48dc31d"
        },
        "last_edited_by": {
          "object": "user",
          "id": "20a7795c-3622-4527-bd13-5ddbf48dc31d"
        },
        "has_children": false,
        "in_trash": false,
        "type": "paragraph",
        "paragraph": {
          "rich_text": [],
          "icon": null,
          "color": "default"
        },
        "archived": false
      }
    },
    {
      "id": "d6d0f8ee-e836-4631-a13b-aaa847e1b80c",
      "type": "paragraph",
      "text": "The suggested methods outperform all other methods considered in the study in the task of identifying students at risk.",
      "raw": {
        "object": "block",
        "id": "d6d0f8ee-e836-4631-a13b-aaa847e1b80c",
        "parent": {
          "type": "page_id",
          "page_id": "eea2d81c-26d2-4925-bc52-9fc707cb7d99"
        },
        "created_time": "2024-08-06T14:33:00.000Z",
        "last_edited_time": "2024-08-06T14:34:00.000Z",
        "created_by": {
          "object": "user",
          "id": "20a7795c-3622-4527-bd13-5ddbf48dc31d"
        },
        "last_edited_by": {
          "object": "user",
          "id": "20a7795c-3622-4527-bd13-5ddbf48dc31d"
        },
        "has_children": false,
        "in_trash": false,
        "type": "paragraph",
        "paragraph": {
          "rich_text": [
            {
              "type": "text",
              "text": {
                "content": "The suggested methods outperform all other methods considered in the study in the task of identifying students at risk.",
                "link": null
              },
              "annotations": {
                "bold": false,
                "italic": false,
                "strikethrough": false,
                "underline": false,
                "code": false,
                "color": "default"
              },
              "plain_text": "The suggested methods outperform all other methods considered in the study in the task of identifying students at risk.",
              "href": null
            }
          ],
          "icon": null,
          "color": "default"
        },
        "archived": false
      }
    },
    {
      "id": "1e24750c-f3ba-80b4-9716-c8a1210ec495",
      "type": "heading_2",
      "text": "Summary Table PRED",
      "raw": {
        "object": "block",
        "id": "1e24750c-f3ba-80b4-9716-c8a1210ec495",
        "parent": {
          "type": "page_id",
          "page_id": "eea2d81c-26d2-4925-bc52-9fc707cb7d99"
        },
        "created_time": "2025-04-27T00:11:00.000Z",
        "last_edited_time": "2025-04-27T00:11:00.000Z",
        "created_by": {
          "object": "user",
          "id": "20a7795c-3622-4527-bd13-5ddbf48dc31d"
        },
        "last_edited_by": {
          "object": "user",
          "id": "20a7795c-3622-4527-bd13-5ddbf48dc31d"
        },
        "has_children": false,
        "in_trash": false,
        "type": "heading_2",
        "heading_2": {
          "rich_text": [
            {
              "type": "text",
              "text": {
                "content": "Summary Table PRED",
                "link": null
              },
              "annotations": {
                "bold": false,
                "italic": false,
                "strikethrough": false,
                "underline": false,
                "code": false,
                "color": "default"
              },
              "plain_text": "Summary Table PRED",
              "href": null
            }
          ],
          "is_toggleable": false,
          "color": "default"
        },
        "archived": false
      }
    },
    {
      "id": "1e24750c-f3ba-8085-aaae-ec2eb2bf83fa",
      "type": "table",
      "text": "",
      "raw": {
        "object": "block",
        "id": "1e24750c-f3ba-8085-aaae-ec2eb2bf83fa",
        "parent": {
          "type": "page_id",
          "page_id": "eea2d81c-26d2-4925-bc52-9fc707cb7d99"
        },
        "created_time": "2025-04-27T00:11:00.000Z",
        "last_edited_time": "2025-04-27T00:11:00.000Z",
        "created_by": {
          "object": "user",
          "id": "20a7795c-3622-4527-bd13-5ddbf48dc31d"
        },
        "last_edited_by": {
          "object": "user",
          "id": "20a7795c-3622-4527-bd13-5ddbf48dc31d"
        },
        "has_children": true,
        "in_trash": false,
        "type": "table",
        "table": {
          "table_width": 16,
          "has_column_header": false,
          "has_row_header": false
        },
        "archived": false
      }
    }
  ]
}