{
  "references": [
    {
      "id": "ce7c642e-062c-424b-bf37-b4c7ab778cc4",
      "title": "ANN-LSTM: A deep learning model for early student performance prediction in MOOC",
      "authors": [],
      "year": null,
      "journal": "Heliyon",
      "doi": null,
      "url": null,
      "zotero_key": null,
      "abstract": null,
      "item_type": null,
      "tags": [],
      "provenance": null
    }
  ],
  "tasks": [],
  "reference_tasks": [],
  "task_extractions": [
    {
      "id": "ex_f1c4e0bd",
      "reference_task_id": null,
      "schema_name": "Summary Table PRED",
      "extracted": [
        {
          "Task": "Classification",
          "Context": "Higher Education",
          "Teaching Method": "E-Learning",
          "Student Performance Definition": "End of Course Performance",
          "Target": "Distinction, Pass, Fail, Withdrawn",
          "Students": "32593 OULAD learners",
          "Courses": "7 courses in OULAD",
          "Data sources": "LMS logs,\nStudent Demographics, ",
          "Features": "[Sequences of Daily Interactions]",
          "Moment of Prediction": "One attempt per Day of Course Duration (270 days in total)",
          "Preprocessing Details": "The work starts with the extraction of the data from OULAD. \n\nAuthors used One-Hot Encoding and Normalization.",
          "Models": "LSTM-ANN,\nRNN, \nGRU,\nMLP, \nRandom Forest, \nAML\n",
          "Assessment Strategy": "Holdout Method",
          "Performance Metric: Best Model": "Day 35\n{Accuracy: 0.6358 - ANN-LSTM, Precision: 0.75 - ANN-LSTM, Recall: 0.41 - ANN-LSTM, F1-Score: 0.52 - ANN-LSTM}\n\nDay 70\n{Accuracy: 0.6804 - ANN-LSTM, Precision: 0.80 - ANN-LSTM, Recall: 0.47 - ANN-LSTM, F1-Score: 0.58 - ANN-LSTM}\n\nDay 105\n{Accuracy: 0.6980 - ANN-LSTM, Precision: 0.81 - ANN-LSTM, Recall: 0.50 - ANN-LSTM, F1-Score: 0.61 - ANN-LSTM}\n\nDay 140\n{Accuracy: 0.7046 - ANN-LSTM, Precision: 0.80 - ANN-LSTM, Recall: 0.53 - ANN-LSTM, F1-Score: 0.64 - ANN-LSTM}\n\nDay 175\n{Accuracy: 0.7135 - ANN-LSTM, Precision: 0.81 - ANN-LSTM, Recall: 0.57 - ANN-LSTM, F1-Score: 0.67 - ANN-LSTM}",
          "Comments": "In total, the authors perform 270 experiments. Each experiment relates to having one dataset starting at Day 1 and Finishing at each day throughout the course duration.\n\nAuthors show that model performance increases with longer datasets.\n\nAccuracy is computed for every day of prediction. Authors make 2 different sets of comparisons:\n\n1- ANN-LSTM vs other DL baselines - GRU and RNN, \n2. ANN - LSTM versus other State-of-the -art architectures: MLP, RF and AML.\n\nIn both scenarios, ANN-LSTM outperforms the other modells. ",
          "Limitations": "Holdout Method, \n\nComputational Times for Deep Learning, which hinders a model’s ability to be used as an EWS. "
        }
      ],
      "provenance": {
        "page_id": "ce7c642e-062c-424b-bf37-b4c7ab778cc4",
        "block_index": 8
      },
      "revision_status": null
    }
  ],
  "annotations": [
    {
      "id": "an_7de87f03",
      "reference_id": "ce7c642e-062c-424b-bf37-b4c7ab778cc4",
      "text": "There is a problem with current classifiers of performance as they often are done in a course or a small subset of courses at the end of the course. Moreover, binary classification seems to be the preferred task. Thses limitations hinder the ability to provide meaningful feedback and student support. ",
      "provenance": {
        "page_id": "ce7c642e-062c-424b-bf37-b4c7ab778cc4"
      }
    },
    {
      "id": "an_c0d62f00",
      "reference_id": "ce7c642e-062c-424b-bf37-b4c7ab778cc4",
      "text": "To address this gap, authors propose a day-wise model to predict performance called ANN-LSTM. Model was compared against a baseline RNN and baseline GRU model. Moreover, results were compared against other state-of-the-art methods. During model testing, it was found that, by the 3rd month of a course, ANN-LSTM obliterated the baselines, achieving 70% accuracy in comparison with the 53% and 56% of RNN and GRU.",
      "provenance": {
        "page_id": "ce7c642e-062c-424b-bf37-b4c7ab778cc4"
      }
    },
    {
      "id": "an_c1d3bea1",
      "reference_id": "ce7c642e-062c-424b-bf37-b4c7ab778cc4",
      "text": "In addition, the model also outperformed the state-of-the art models between 6% and 14%, showing LSTM as an effective way to model temporal relationships in the data.",
      "provenance": {
        "page_id": "ce7c642e-062c-424b-bf37-b4c7ab778cc4"
      }
    }
  ],
  "workflow_states": []
}